virapi_middlewares/cors.py
virapi_middlewares/csp.py
virapi_middlewares/exception.py
virapi_middlewares/g_zip.py
virapi_middlewares/http_headers.py
virapi_middlewares/https_redirect.py
virapi_middlewares/rate_limit.py
virapi_middlewares/trusted_host.py
virapi_middlewares-0.1.0.dist-info/METADATA
virapi_middlewares-0.1.0.dist-info/WHEEL
virapi_middlewares-0.1.0.dist-info/top_level.txt
virapi_middlewares-0.1.0.dist-info/RECORD
