Metadata-Version: 2.4
Name: virapi_middlewares
Version: 0.1.0
Summary: Middleware implementation for Virapi.
Author-email: Víctor Gómez <mdsuanzes@gmail.com>
License-Expression: MIT
Requires-Python: >=3.9
Requires-Dist: virapi
